openfeed/__init__.py
openfeed/openfeed_client.py
openfeed/version.py
openfeed/generated/openfeed_api_pb2.py
openfeed/generated/openfeed_api_pb2.pyi
openfeed/generated/openfeed_instrument_pb2.py
openfeed/generated/openfeed_instrument_pb2.pyi
openfeed/generated/openfeed_pb2.py
openfeed/generated/openfeed_pb2.pyi
protos/README.md
openfeed-1.4.0.dist-info/LICENSE
openfeed-1.4.0.dist-info/METADATA
openfeed-1.4.0.dist-info/WHEEL
openfeed-1.4.0.dist-info/top_level.txt
openfeed-1.4.0.dist-info/RECORD
