Metadata-Version: 2.1
Name: openfeed
Version: 1.4.0
Summary: Barchart Openfeed Example Client for Python
Home-page: https://github.com/openfeed-org/sdk-python
Download-URL: https://github.com/openfeed-org/sdk-python/archive/master.zip
Author: Barchart
Author-email: openfeed@barchart.com
License: MIT
License-File: LICENSE
Requires-Dist: websocket-client >=0.40.0
Requires-Dist: protobuf
Provides-Extra: test
Requires-Dist: pytest ; extra == 'test'
Requires-Dist: python-dateutil >=2.7.5 ; extra == 'test'
